proofdock/rp/contrib/django/__init__.py
proofdock/rp/contrib/django/config.py
proofdock/rp/contrib/django/middleware.py
proofdock/rp/contrib/django/version.py
proofdock_reliability_platform_django-1.0.0.dist-info/METADATA
proofdock_reliability_platform_django-1.0.0.dist-info/WHEEL
proofdock_reliability_platform_django-1.0.0.dist-info/top_level.txt
proofdock_reliability_platform_django-1.0.0.dist-info/RECORD
