Metadata-Version: 2.1
Name: proofdock-reliability-platform-django
Version: 1.0.0
Summary: A reliability platform client for Django applications.
Home-page: https://github.com/proofdock/chaos-middleware-python/tree/master/src/contrib-django
Author: Proofdock Authors
Author-email: support@proofdock.io
License: Apache-2.0
Platform: UNKNOWN
Classifier: Intended Audience :: Developers
Classifier: Development Status :: 4 - Beta
Classifier: Intended Audience :: Developers
Classifier: License :: OSI Approved :: Apache Software License
Classifier: Programming Language :: Python
Classifier: Programming Language :: Python :: 3
Classifier: Programming Language :: Python :: 3.5
Classifier: Programming Language :: Python :: 3.6
Classifier: Programming Language :: Python :: 3.7
Classifier: Programming Language :: Python :: 3.8
Requires-Python: >=3.5.*
Requires-Dist: django
Requires-Dist: proofdock-reliability-platform-core
